msmhelper/__init__.py
msmhelper/__main__.py
msmhelper/io.py
msmhelper/statetraj.py
msmhelper/_cli/__init__.py
msmhelper/_cli/ck_test.py
msmhelper/_cli/compare_discretization.py
msmhelper/_cli/contact_rep.py
msmhelper/_cli/dynamical_coring.py
msmhelper/_cli/gaussian_filter.py
msmhelper/_cli/implied_timescales.py
msmhelper/_cli/waiting_time_dist.py
msmhelper/_cli/waiting_times.py
msmhelper/md/__init__.py
msmhelper/md/comparison.py
msmhelper/md/corrections.py
msmhelper/md/timescales.py
msmhelper/msm/__init__.py
msmhelper/msm/msm.py
msmhelper/msm/tests.py
msmhelper/msm/timescales.py
msmhelper/msm/utils/__init__.py
msmhelper/msm/utils/linalg.py
msmhelper/plot/__init__.py
msmhelper/plot/_ck_test.py
msmhelper/plot/_wtd.py
msmhelper/utils/__init__.py
msmhelper/utils/_utils.py
msmhelper/utils/datasets.py
msmhelper/utils/filtering.py
msmhelper/utils/tests.py
msmhelper-1.1.1.dist-info/LICENSE
msmhelper-1.1.1.dist-info/METADATA
msmhelper-1.1.1.dist-info/WHEEL
msmhelper-1.1.1.dist-info/entry_points.txt
msmhelper-1.1.1.dist-info/top_level.txt
msmhelper-1.1.1.dist-info/RECORD
