Metadata-Version: 2.1
Name: msmhelper
Version: 1.1.1
Summary: Helper functions for Markov State Models.
Home-page: https://github.com/moldyn/msmhelper
Author: braniii
License: BSD-3-Clause License
Project-URL: Documentation, https://moldyn.github.io/msmhelper
Project-URL: Source Code, https://github.com/moldyn/msmhelper
Project-URL: Changelog, https://moldyn.github.io/msmhelper/changelog
Project-URL: Bug Tracker, https://github.com/moldyn/msmhelper/issues
Keywords: MSM,Markov model,Markov state model,MD analysis
Classifier: License :: OSI Approved :: BSD License
Classifier: Intended Audience :: Science/Research
Classifier: Natural Language :: English
Classifier: Programming Language :: Python :: 3
Classifier: Programming Language :: Python :: 3.8
Classifier: Programming Language :: Python :: 3.9
Classifier: Programming Language :: Python :: 3.10
Classifier: Programming Language :: Python :: 3.11
Classifier: Topic :: Scientific/Engineering :: Physics
Classifier: Topic :: Scientific/Engineering :: Bio-Informatics
Classifier: Topic :: Software Development :: Libraries :: Python Modules
Requires-Python: >=3.8
License-File: LICENSE
Requires-Dist: numpy >=1.21
Requires-Dist: numba >=0.57
Requires-Dist: pandas
Requires-Dist: decorit
Requires-Dist: scipy
Requires-Dist: click
Requires-Dist: prettypyplot
Provides-Extra: all
Requires-Dist: mkdocs-literate-nav ; extra == 'all'
Requires-Dist: mkdocs-click ; extra == 'all'
Requires-Dist: pytest ; extra == 'all'
Requires-Dist: pytest-cov ; extra == 'all'
Requires-Dist: notebook <7.0.0,>=6.4.12 ; extra == 'all'
Requires-Dist: mkdocs-material ; extra == 'all'
Requires-Dist: mkdocstrings-python ; extra == 'all'
Requires-Dist: mkdocs-jupyter ; extra == 'all'
Requires-Dist: jupyter-contrib-nbextensions ; extra == 'all'
Requires-Dist: flake8 ; extra == 'all'
Requires-Dist: mkdocs-section-index ; extra == 'all'
Requires-Dist: pyemma ; extra == 'all'
Requires-Dist: mkdocs-gen-files ; extra == 'all'
Requires-Dist: pytest-rerunfailures ; extra == 'all'
Requires-Dist: mkdocstrings ; extra == 'all'
Requires-Dist: pytest-mpl ; extra == 'all'
Provides-Extra: docs
Requires-Dist: mkdocs-literate-nav ; extra == 'docs'
Requires-Dist: mkdocs-click ; extra == 'docs'
Requires-Dist: notebook <7.0.0,>=6.4.12 ; extra == 'docs'
Requires-Dist: mkdocs-material ; extra == 'docs'
Requires-Dist: mkdocstrings-python ; extra == 'docs'
Requires-Dist: mkdocs-jupyter ; extra == 'docs'
Requires-Dist: jupyter-contrib-nbextensions ; extra == 'docs'
Requires-Dist: mkdocs-section-index ; extra == 'docs'
Requires-Dist: pyemma ; extra == 'docs'
Requires-Dist: mkdocstrings ; extra == 'docs'
Requires-Dist: mkdocs-gen-files ; extra == 'docs'
Provides-Extra: testing
Requires-Dist: pytest ; extra == 'testing'
Requires-Dist: pytest-cov ; extra == 'testing'
Requires-Dist: flake8 ; extra == 'testing'
Requires-Dist: pytest-rerunfailures ; extra == 'testing'
Requires-Dist: pytest-mpl ; extra == 'testing'
